imagetune/__init__.py
imagetune/helper_functions.py
imagetune/imagetune.py
imagetune/ui.py
imagetune-0.1.0.dist-info/METADATA
imagetune-0.1.0.dist-info/WHEEL
imagetune-0.1.0.dist-info/top_level.txt
imagetune-0.1.0.dist-info/RECORD
