Metadata-Version: 2.4
Name: imagetune
Version: 0.1.0
Summary: Live tuning of image processing algorithms
Author-email: "Julius B. Kirkegaard" <juki@di.ku.dk>
License-Expression: GPL-3.0-or-later
Project-URL: Homepage, https://github.com/juliusbierk/imagetune
Project-URL: Repository, https://github.com/juliusbierk/imagetune
Project-URL: Issues, https://github.com/juliusbierk/imagetune/issues
Requires-Python: >=3.10
Requires-Dist: numpy
Requires-Dist: fastplotlib
Requires-Dist: PyQt6
Requires-Dist: PySide6
